juno_dkt/__init__.py
juno_dkt/utils.py
juno_dkt-0.8.15.dist-info/METADATA
juno_dkt-0.8.15.dist-info/WHEEL
juno_dkt-0.8.15.dist-info/top_level.txt
juno_dkt-0.8.15.dist-info/RECORD
