Metadata-Version: 2.1
Name: juno-dkt
Version: 0.8.15
Summary: Scikit-learn style implementation of Deep Knowledge Tracing models based on pytorch.
Home-page: https://github.com/juno-hwang/juno-dkt
Author: Juno Hwang
Author-email: wnsdh10@snu.ac.kr
License: UNKNOWN
Platform: UNKNOWN
Classifier: Programming Language :: Python :: 3
Classifier: License :: OSI Approved :: MIT License
Classifier: Operating System :: OS Independent
Requires-Python: >=3.6
Requires-Dist: numpy
Requires-Dist: pandas
Requires-Dist: scikit-learn
Requires-Dist: tqdm
Requires-Dist: networkx
